{"metadata": "Top gainers, losers, and most actively traded US tickers", "last_updated": "2024-10-24 16:15:59 US/Eastern", "top_gainers": [{"ticker": "MNPR", "price": "32.66", "change_amount": "28.03", "change_percentage": "605.3996%", "volume": "19064245"}, {"ticker": "NXU", "price": "0.5986", "change_amount": "0.3478", "change_percentage": "138.6762%", "volume": "390609776"}, {"ticker": "NXLIW", "price": "0.325", "change_amount": "0.185", "change_percentage": "132.1429%", "volume": "145027"}, {"ticker": "ZCARW", "price": "0.0185", "change_amount": "0.0097", "change_percentage": "110.2273%", "volume": "425242"}, {"ticker": "EDBLW", "price": "0.0156", "change_amount": "0.008", "change_percentage": "105.2632%", "volume": "600"}, {"ticker": "XBPEW", "price": "0.06", "change_amount": "0.03", "change_percentage": "100.0%", "volume": "130719"}, {"ticker": "DPCSW", "price": "0.0269", "change_amount": "0.0132", "change_percentage": "96.3504%", "volume": "1103"}, {"ticker": "HUBCZ", "price": "0.0049", "change_amount": "0.0024", "change_percentage": "96.0%", "volume": "88278"}, {"ticker": "EFSH", "price": "3.17", "change_amount": "1.55", "change_percentage": "95.679%", "volume": "33861935"}, {"ticker": "FORLW", "price": "0.09", "change_amount": "0.0399", "change_percentage": "79.6407%", "volume": "1501"}, {"ticker": "OPTXW", "price": "0.07", "change_amount": "0.0294", "change_percentage": "72.4138%", "volume": "1035"}, {"ticker": "NMHIW", "price": "0.029", "change_amount": "0.0121", "change_percentage": "71.5976%", "volume": "8170"}, {"ticker": "ATMCR", "price": "0.22", "change_amount": "0.09", "change_percentage": "69.2308%", "volume": "1181"}, {"ticker": "LIFWW", "price": "0.0033", "change_amount": "0.0013", "change_percentage": "65.0%", "volume": "641498"}, {"ticker": "YOTAR", "price": "0.145", "change_amount": "0.0549", "change_percentage": "60.9323%", "volume": "119645"}, {"ticker": "GDEVW", "price": "0.05", "change_amount": "0.0189", "change_percentage": "60.7717%", "volume": "72010"}, {"ticker": "NXL", "price": "2.15", "change_amount": "0.785", "change_percentage": "57.5092%", "volume": "28223107"}, {"ticker": "ATGL", "price": "9.65", "change_amount": "3.32", "change_percentage": "52.4487%", "volume": "1383170"}, {"ticker": "IVCAW", "price": "0.075", "change_amount": "0.025", "change_percentage": "50.0%", "volume": "22867"}, {"ticker": "WBX+", "price": "0.12", "change_amount": "0.04", "change_percentage": "50.0%", "volume": "9444"}], "top_losers": [{"ticker": "MRNS", "price": "0.296", "change_amount": "-1.394", "change_percentage": "-82.4852%", "volume": "47395725"}, {"ticker": "VSACW", "price": "0.0002", "change_amount": "-0.0009", "change_percentage": "-81.8182%", "volume": "106553"}, {"ticker": "LILMW", "price": "0.0162", "change_amount": "-0.0602", "change_percentage": "-78.7958%", "volume": "1927716"}, {"ticker": "ORKT", "price": "1.85", "change_amount": "-5.76", "change_percentage": "-75.6899%", "volume": "17245385"}, {"ticker": "HOFVW", "price": "0.0042", "change_amount": "-0.0096", "change_percentage": "-69.5652%", "volume": "111275"}, {"ticker": "SXTPW", "price": "0.015", "change_amount": "-0.0249", "change_percentage": "-62.406%", "volume": "13"}, {"ticker": "LILM", "price": "0.2094", "change_amount": "-0.3345", "change_percentage": "-61.5003%", "volume": "113111965"}, {"ticker": "GORO", "price": "0.1987", "change_amount": "-0.296", "change_percentage": "-59.8342%", "volume": "18404855"}, {"ticker": "EMCGW", "price": "0.0138", "change_amount": "-0.0115", "change_percentage": "-45.4545%", "volume": "1000"}, {"ticker": "FOXXW", "price": "0.1511", "change_amount": "-0.1224", "change_percentage": "-44.7532%", "volume": "632"}, {"ticker": "TSLZ", "price": "8.33", "change_amount": "-6.53", "change_percentage": "-43.9435%", "volume": "27945481"}, {"ticker": "TSLQ", "price": "15.0", "change_amount": "-11.75", "change_percentage": "-43.9252%", "volume": "21159903"}, {"ticker": "TSDD", "price": "5.38", "change_amount": "-4.16", "change_percentage": "-43.6059%", "volume": "13677537"}, {"ticker": "COEPW", "price": "0.0226", "change_amount": "-0.0171", "change_percentage": "-43.073%", "volume": "13002"}, {"ticker": "CYTHW", "price": "0.14", "change_amount": "-0.1", "change_percentage": "-41.6667%", "volume": "1405"}, {"ticker": "PC", "price": "0.8277", "change_amount": "-0.5623", "change_percentage": "-40.4532%", "volume": "2503903"}, {"ticker": "SVRE", "price": "0.0871", "change_amount": "-0.0586", "change_percentage": "-40.2196%", "volume": "11683975"}, {"ticker": "PHUN", "price": "8.48", "change_amount": "-5.66", "change_percentage": "-40.0283%", "volume": "33855650"}, {"ticker": "KWE", "price": "1.5", "change_amount": "-1.0", "change_percentage": "-40.0%", "volume": "702782"}, {"ticker": "CAPTW", "price": "0.03", "change_amount": "-0.02", "change_percentage": "-40.0%", "volume": "107231"}], "most_actively_traded": [{"ticker": "NXU", "price": "0.5986", "change_amount": "0.3478", "change_percentage": "138.6762%", "volume": "390609776"}, {"ticker": "TSLA", "price": "260.48", "change_amount": "46.83", "change_percentage": "21.919%", "volume": "200939512"}, {"ticker": "LGCB", "price": "0.333", "change_amount": "0.0655", "change_percentage": "24.486%", "volume": "181571763"}, {"ticker": "NVDA", "price": "140.41", "change_amount": "0.85", "change_percentage": "0.6091%", "volume": "170828445"}, {"ticker": "TSLL", "price": "12.95", "change_amount": "3.94", "change_percentage": "43.7292%", "volume": "148932015"}, {"ticker": "SQQQ", "price": "7.24", "change_amount": "-0.17", "change_percentage": "-2.2942%", "volume": "131568640"}, {"ticker": "LILM", "price": "0.2094", "change_amount": "-0.3345", "change_percentage": "-61.5003%", "volume": "113111965"}, {"ticker": "WULF", "price": "6.21", "change_amount": "-0.19", "change_percentage": "-2.9687%", "volume": "87819869"}, {"ticker": "QLGN", "price": "0.1081", "change_amount": "-0.0659", "change_percentage": "-37.8736%", "volume": "82652307"}, {"ticker": "SOFI", "price": "10.93", "change_amount": "0.51", "change_percentage": "4.8944%", "volume": "71515334"}, {"ticker": "CNSP", "price": "0.1456", "change_amount": "0.0046", "change_percentage": "3.2624%", "volume": "70359350"}, {"ticker": "QS", "price": "6.5", "change_amount": "1.32", "change_percentage": "25.4826%", "volume": "68929399"}, {"ticker": "AAL", "price": "12.78", "change_amount": "-0.05", "change_percentage": "-0.3897%", "volume": "65261389"}, {"ticker": "SOXL", "price": "34.27", "change_amount": "0.47", "change_percentage": "1.3905%", "volume": "59436825"}, {"ticker": "ZENA", "price": "2.16", "change_amount": "0.4", "change_percentage": "22.7273%", "volume": "54830336"}, {"ticker": "NIO", "price": "4.98", "change_amount": "-0.21", "change_percentage": "-4.0462%", "volume": "48111583"}, {"ticker": "MARA", "price": "18.22", "change_amount": "0.15", "change_percentage": "0.8301%", "volume": "47824978"}, {"ticker": "MRNS", "price": "0.296", "change_amount": "-1.394", "change_percentage": "-82.4852%", "volume": "47395725"}, {"ticker": "TVGN", "price": "2.56", "change_amount": "0.08", "change_percentage": "3.2258%", "volume": "45979664"}, {"ticker": "F", "price": "11.23", "change_amount": "0.17", "change_percentage": "1.5371%", "volume": "44298102"}]}